setup.py
km_plugin_interface_api/__init__.py
km_plugin_interface_api/interface_api.py
km_plugin_interface_api.egg-info/PKG-INFO
km_plugin_interface_api.egg-info/SOURCES.txt
km_plugin_interface_api.egg-info/dependency_links.txt
km_plugin_interface_api.egg-info/entry_points.txt
km_plugin_interface_api.egg-info/requires.txt
km_plugin_interface_api.egg-info/top_level.txt